eth_hash/__init__.py
eth_hash/abc.py
eth_hash/auto.py
eth_hash/main.py
eth_hash/py.typed
eth_hash/utils.py
eth_hash/backends/__init__.py
eth_hash/backends/auto.py
eth_hash/backends/pycryptodome.py
eth_hash/backends/pysha3.py
eth_hash-0.7.0.dist-info/LICENSE
eth_hash-0.7.0.dist-info/METADATA
eth_hash-0.7.0.dist-info/WHEEL
eth_hash-0.7.0.dist-info/top_level.txt
eth_hash-0.7.0.dist-info/RECORD
